[
  {
    "albumID" : "1689116931",
    "artist" : "Van Dusen",
    "duration" : 3917.4679999999994,
    "releaseDate" : 708566400,
    "title" : "Folge 1: Der süße Duft des Todes",
    "upc" : "4260507186508"
  },
  {
    "albumID" : "1694835362",
    "artist" : "Van Dusen",
    "duration" : 3929.2229999999995,
    "releaseDate" : 708566400,
    "title" : "Folge 2: Dunkle Pfade 1",
    "upc" : "4260507186522"
  },
  {
    "albumID" : "1693257784",
    "artist" : "Van Dusen",
    "duration" : 5010.249,
    "releaseDate" : 714614400,
    "title" : "Folge 17: Wir jagten Mister Noir",
    "upc" : "4260507187611"
  },
  {
    "albumID" : "1689124978",
    "artist" : "Van Dusen",
    "duration" : 3401.719000000001,
    "releaseDate" : 708566400,
    "title" : "Folge 5: Sturmnacht 1",
    "upc" : "4260507186584"
  },
  {
    "albumID" : "1706853539",
    "artist" : "Van Dusen",
    "duration" : 5442.502000000001,
    "releaseDate" : 721267200,
    "title" : "Folge 21: Das Van Dusen-Gambit",
    "upc" : "4260507189301"
  },
  {
    "albumID" : "1689131494",
    "artist" : "Van Dusen",
    "duration" : 3832.719000000001,
    "releaseDate" : 709171200,
    "title" : "Folge 7: Höllenfahrt",
    "upc" : "4260507186621"
  },
  {
    "albumID" : "1689126107",
    "artist" : "Van Dusen",
    "duration" : 5304.469,
    "releaseDate" : 710380800,
    "title" : "Folge 16: Weiße Kittel - Rotes Blut",
    "upc" : "4260507186805"
  },
  {
    "albumID" : "1689120412",
    "artist" : "Van Dusen",
    "duration" : 3976.718,
    "releaseDate" : 709171200,
    "title" : "Folge 9: Tatsächlich ... Mord!",
    "upc" : "4260507186669"
  },
  {
    "albumID" : "1689126854",
    "artist" : "Van Dusen",
    "duration" : 3765.72,
    "releaseDate" : 708566400,
    "title" : "Folge 4: Der Käfig",
    "upc" : "4260507186560"
  },
  {
    "albumID" : "1754120172",
    "artist" : "Van Dusen",
    "duration" : 4034.4799999999996,
    "releaseDate" : 745459200,
    "title" : "Folge 31: Das letzte Geheimnis der Titanic",
    "upc" : "4260507196934"
  },
  {
    "albumID" : "1693261265",
    "artist" : "Van Dusen",
    "duration" : 5045.500999999999,
    "releaseDate" : 715219200,
    "title" : "Folge 18: Schlafende Hunde",
    "upc" : "4260507187635"
  },
  {
    "albumID" : "1764891009",
    "artist" : "Van Dusen",
    "duration" : 4452.710999999998,
    "releaseDate" : 750297600,
    "title" : "Folge 33: Verzockt",
    "upc" : "4260507198686"
  },
  {
    "albumID" : "1689128163",
    "artist" : "Van Dusen",
    "duration" : 4198.721,
    "releaseDate" : 708566400,
    "title" : "Folge 3: Dunkle Pfade 2",
    "upc" : "4260507186546"
  },
  {
    "albumID" : "1689125492",
    "artist" : "Van Dusen",
    "duration" : 3962.2290000000003,
    "releaseDate" : 709776000,
    "title" : "Folge 13: Mordsdilemma",
    "upc" : "4260507186744"
  },
  {
    "albumID" : "1689126850",
    "artist" : "Van Dusen",
    "duration" : 4323.226,
    "releaseDate" : 709776000,
    "title" : "Folge 11: Engel der Rache",
    "upc" : "4260507186706"
  },
  {
    "albumID" : "1694835254",
    "artist" : "Van Dusen",
    "duration" : 3867.9720000000007,
    "releaseDate" : 709171200,
    "title" : "Folge 8: Das Netz der falschen Witwe",
    "upc" : "4260507186645"
  },
  {
    "albumID" : "1689125264",
    "artist" : "Van Dusen",
    "duration" : 4883.468000000002,
    "releaseDate" : 709776000,
    "title" : "Folge 14: Vom Leben und vom Sterben",
    "upc" : "4260507186768"
  },
  {
    "albumID" : "1739127246",
    "artist" : "Van Dusen",
    "duration" : 4450.751,
    "releaseDate" : 736387200,
    "title" : "Folge 28: Freunde fürs Sterben",
    "upc" : "4260507194619"
  },
  {
    "albumID" : "1694835390",
    "artist" : "Van Dusen",
    "duration" : 3619.2239999999997,
    "releaseDate" : 709171200,
    "title" : "Folge 10: Die Party des Jahres",
    "upc" : "4260507186683"
  },
  {
    "albumID" : "1689126608",
    "artist" : "Van Dusen",
    "duration" : 4311.094,
    "releaseDate" : 709776000,
    "title" : "Folge 12: Mörder unter sich",
    "upc" : "4260507186720"
  },
  {
    "albumID" : "1725810269",
    "artist" : "Van Dusen",
    "duration" : 4673.362000000001,
    "releaseDate" : 732153600,
    "title" : "Folge 26: Das Kuckucksei",
    "upc" : "4260507192349"
  },
  {
    "albumID" : "1725809262",
    "artist" : "Van Dusen",
    "duration" : 5182.313999999999,
    "releaseDate" : 731548800,
    "title" : "Folge 25: Quo vadis, Augustus?",
    "upc" : "4260507192325"
  },
  {
    "albumID" : "1689123612",
    "artist" : "Van Dusen",
    "duration" : 4887.959999999997,
    "releaseDate" : 709776000,
    "title" : "Folge 15: Tod eines Bastards",
    "upc" : "4260507186782"
  },
  {
    "albumID" : "1694379130",
    "artist" : "Van Dusen",
    "duration" : 4937.998,
    "releaseDate" : 717638400,
    "title" : "Folge 19: Kammerspiel",
    "upc" : "4260507187949"
  },
  {
    "albumID" : "1705774471",
    "artist" : "Van Dusen",
    "duration" : 4015.4990000000003,
    "releaseDate" : 718243200,
    "title" : "Folge 20: Haben Sie Vernon gesehen?",
    "upc" : "4260507188502"
  },
  {
    "albumID" : "1743837151",
    "artist" : "Van Dusen",
    "duration" : 4127.966,
    "releaseDate" : 742435200,
    "title" : "Folge 29: Abgründe",
    "upc" : "4260507195395"
  },
  {
    "albumID" : "1694835619",
    "artist" : "Van Dusen",
    "duration" : 3575.5999999999995,
    "releaseDate" : 709171200,
    "title" : "Folge 6: Sturmnacht 2",
    "upc" : "4260507186607"
  },
  {
    "albumID" : "1757443991",
    "artist" : "Van Dusen",
    "duration" : 4256.024,
    "releaseDate" : 747878400,
    "title" : "Folge 32: Mord am Lake",
    "upc" : "4260507198075"
  },
  {
    "albumID" : "1712121279",
    "artist" : "Van Dusen",
    "duration" : 4426.996999999999,
    "releaseDate" : 722476800,
    "title" : "Folge 22: Beim ersten Spatenstich",
    "upc" : "4260507190260"
  },
  {
    "albumID" : "1719590181",
    "artist" : "Van Dusen",
    "duration" : 5370.999999999999,
    "releaseDate" : 727315200,
    "title" : "Folge 24: Der schwarze Turm",
    "upc" : "4260507191304"
  },
  {
    "albumID" : "1751255774",
    "artist" : "Van Dusen",
    "duration" : 3612.8259999999996,
    "releaseDate" : 743644800,
    "title" : "Folge 30: Das Ende, das ein Anfang war",
    "upc" : "4260507196323"
  },
  {
    "albumID" : "1714236136",
    "artist" : "Van Dusen",
    "duration" : 4525.997,
    "releaseDate" : 724896000,
    "title" : "Folge 23: Was wirklich mit Judy geschah",
    "upc" : "4260507190765"
  },
  {
    "albumID" : "1739121349",
    "artist" : "Van Dusen",
    "duration" : 4179.9980000000005,
    "releaseDate" : 735177600,
    "title" : "Folge 27: Ihr letzter Tanz",
    "upc" : "4260507194084"
  },
  {
    "albumID" : "1771495401",
    "artist" : "Van Dusen",
    "duration" : 184.637,
    "releaseDate" : 753321600,
    "title" : "Folge 34: Die Mörderin",
    "upc" : "4260507199447"
  },
  {
    "albumID" : "1776695885",
    "artist" : "Van Dusen",
    "duration" : 183.95999999999998,
    "releaseDate" : 756950400,
    "title" : "Folge 35: Die Schatulle",
    "upc" : "4260507200297"
  }
]