[
  {
    "albumID" : "1510357716",
    "artist" : "VIDAN",
    "duration" : 2396.055,
    "releaseDate" : 610588800,
    "title" : "Staffel 1: Schrei nach Leben - Original Soundtrack",
    "upc" : "886448430643"
  },
  {
    "albumID" : "1700905912",
    "artist" : "VIDAN",
    "duration" : 3528.1079999999997,
    "releaseDate" : 717638400,
    "title" : "Staffel 3: Schrei nach Vernichtung, Folge 5: Flehende Seelen",
    "upc" : "196871108461"
  },
  {
    "albumID" : "1700925166",
    "artist" : "VIDAN",
    "duration" : 3237.374,
    "releaseDate" : 717638400,
    "title" : "Staffel 3: Schrei nach Vernichtung, Folge 7: Caja Sorpresa",
    "upc" : "196871108522"
  },
  {
    "albumID" : "1700906341",
    "artist" : "VIDAN",
    "duration" : 2755.1609999999996,
    "releaseDate" : 717638400,
    "title" : "Folge 8: Die Gesandte (Staffel 3: Schrei nach Vernichtung)",
    "upc" : "196871108560"
  },
  {
    "albumID" : "1700906725",
    "artist" : "VIDAN",
    "duration" : 3501.668,
    "releaseDate" : 717638400,
    "title" : "Staffel 3: Schrei nach Vernichtung, Folge 9: Nootaus Kampf",
    "upc" : "196871108614"
  },
  {
    "albumID" : "1700907151",
    "artist" : "VIDAN",
    "duration" : 4473.268000000001,
    "releaseDate" : 717638400,
    "title" : "Staffel 3: Schrei nach Vernichtung, Folge 10: Überleben?",
    "upc" : "196871108652"
  }
]